obsidianhtml/README.md
obsidianhtml/SharedResources.py
obsidianhtml/__init__.py
obsidianhtml/__main__.py
obsidianhtml/lib.py
obsidianhtml/compiler/HTML.py
obsidianhtml/compiler/Templating.py
obsidianhtml/compiler/__init__.py
obsidianhtml/compiler/__main__.py
obsidianhtml/controller/Config.py
obsidianhtml/controller/ConvertVault.py
obsidianhtml/controller/Export.py
obsidianhtml/controller/Run.py
obsidianhtml/controller/Serve.py
obsidianhtml/controller/__init__.py
obsidianhtml/controller/__main__.py
obsidianhtml/core/ConfigManager.py
obsidianhtml/core/ErrorHandling.py
obsidianhtml/core/FileFinder.py
obsidianhtml/core/FileObject.py
obsidianhtml/core/Index.py
obsidianhtml/core/NetworkTree.py
obsidianhtml/core/PicknickBasket.py
obsidianhtml/core/Types.py
obsidianhtml/core/__init__.py
obsidianhtml/core/__main__.py
obsidianhtml/core/readme.md
obsidianhtml/features/CreateIndexFromDirStructure.py
obsidianhtml/features/CreateIndexFromTags.py
obsidianhtml/features/EmbeddedSearch.py
obsidianhtml/features/RssFeed.py
obsidianhtml/features/Search.py
obsidianhtml/features/SidePane.py
obsidianhtml/features/__init__.py
obsidianhtml/features/__main__.py
obsidianhtml/features/add_toc_when_missing.py
obsidianhtml/features/post_processing.py
obsidianhtml/gui/Api.py
obsidianhtml/gui/ConfigChecker.py
obsidianhtml/gui/Ledger.py
obsidianhtml/gui/Templater.py
obsidianhtml/gui/WindowManager.py
obsidianhtml/gui/__init__.py
obsidianhtml/gui/__main__.py
obsidianhtml/gui/lib.py
obsidianhtml/gui/readme.md
obsidianhtml/markdown_extensions/AdmonitionExtension.py
obsidianhtml/markdown_extensions/BlockLinkExtension.py
obsidianhtml/markdown_extensions/CallOutExtension.py
obsidianhtml/markdown_extensions/CodeWrapperExtension.py
obsidianhtml/markdown_extensions/CustomTableExtension.py
obsidianhtml/markdown_extensions/CustomTocExtension.py
obsidianhtml/markdown_extensions/DataviewExtension.py
obsidianhtml/markdown_extensions/EmbeddedSearchExtension.py
obsidianhtml/markdown_extensions/EraserExtension.py
obsidianhtml-4.0.1.dist-info/LICENSE
obsidianhtml-4.0.1.dist-info/METADATA
obsidianhtml-4.0.1.dist-info/WHEEL
obsidianhtml-4.0.1.dist-info/entry_points.txt
obsidianhtml-4.0.1.dist-info/top_level.txt
obsidianhtml-4.0.1.dist-info/RECORD
