Metadata-Version: 2.1
Name: obsidianhtml
Version: 4.0.1
Summary: Converts Obsidian notes into proper markdown and HTML
Home-page: https://github.com/obsidian-html/obsidian-html
Author: https://github.com/dwrolvink
Author-email: dwrolvink@protonmail.com
License: GNU General Public License v3 or later (GPLv3+)
Keywords: html,markdown,notes,markdown-to-html,note-taking,obsidian,html-css-javascript,notes-app,obsidian-md,obsidian-html,obsidianmd,obsidian-notes
Classifier: Development Status :: 5 - Production/Stable
Classifier: Programming Language :: Python :: 3.9
Classifier: Intended Audience :: End Users/Desktop
Classifier: License :: OSI Approved :: GNU General Public License v3 or later (GPLv3+)
Requires-Python: >=3.9
License-File: LICENSE
Requires-Dist: markdown >=3.4.1
Requires-Dist: pymdown-extensions
Requires-Dist: python-frontmatter
Requires-Dist: pygments
Requires-Dist: regex
Requires-Dist: requests
Requires-Dist: beautifulsoup4
Requires-Dist: html5lib
Requires-Dist: pywebview
Requires-Dist: appdirs
Requires-Dist: lxml
Requires-Dist: whoosh
